{
    "check-requirements": false,
    "dump-autoload": false,
    "stub": "bin/lsp",
    "output": "var/prod/build.phar",
    "main": false,
    "compression": "GZ",
    "finder": [
        {
            "name": [
                "*.php"
            ],
            "exclude": [
                "Test",
                "test",
                "Tests",
                "tests"
            ],
            "in": [
                "app",
                "config",
                "vendor"
            ]
        }
    ]
}
